jupyterlabcodetoc/__init__.py
jupyterlabcodetoc/_version.py
jupyterlabcodetoc-4.0.1.data/data/share/jupyter/labextensions/jupyterlabcodetoc/package.json
jupyterlabcodetoc-4.0.1.data/data/share/jupyter/labextensions/jupyterlabcodetoc/schemas/jupyterlabcodetoc/package.json.orig
jupyterlabcodetoc-4.0.1.data/data/share/jupyter/labextensions/jupyterlabcodetoc/schemas/jupyterlabcodetoc/registry.json
jupyterlabcodetoc-4.0.1.data/data/share/jupyter/labextensions/jupyterlabcodetoc/static/10.cf1b4fc8cc4ed5441a76.js
jupyterlabcodetoc-4.0.1.data/data/share/jupyter/labextensions/jupyterlabcodetoc/static/558.5a345559e9eb42193fc0.js
jupyterlabcodetoc-4.0.1.data/data/share/jupyter/labextensions/jupyterlabcodetoc/static/629.43cc9ed10da0eddd0859.js
jupyterlabcodetoc-4.0.1.data/data/share/jupyter/labextensions/jupyterlabcodetoc/static/638.3ff5c8a3336695f4c116.js
jupyterlabcodetoc-4.0.1.data/data/share/jupyter/labextensions/jupyterlabcodetoc/static/remoteEntry.b5fc634e4e1e8af6d239.js
jupyterlabcodetoc-4.0.1.data/data/share/jupyter/labextensions/jupyterlabcodetoc/static/style.js
jupyterlabcodetoc-4.0.1.data/data/share/jupyter/labextensions/jupyterlabcodetoc/static/third-party-licenses.json
jupyterlabcodetoc-4.0.1.data/data/share/jupyter/labextensions/jupyterlabcodetoc/install.json
jupyterlabcodetoc-4.0.1.dist-info/METADATA
jupyterlabcodetoc-4.0.1.dist-info/WHEEL
jupyterlabcodetoc-4.0.1.dist-info/licenses/LICENSE
jupyterlabcodetoc-4.0.1.dist-info/RECORD
