Metadata-Version: 2.1
Name: jupyterlabcodetoc
Version: 4.0.1
Summary: JupyterLab Table of Contents extension that includes code cells and markdown content other than headings.
Project-URL: Homepage, https://github.com/Rmarieta/jupyterlab-code-toc
Project-URL: Bug Tracker, https://github.com/Rmarieta/jupyterlab-code-toc/issues
Project-URL: Repository, https://github.com/Rmarieta/jupyterlab-code-toc.git
Author-email: Raphael Marietan <raphael.marietan@gmail.com>
License: BSD 3-Clause License
License-File: LICENSE
Classifier: Framework :: Jupyter
Classifier: Framework :: Jupyter :: JupyterLab
Classifier: Framework :: Jupyter :: JupyterLab :: 4
Classifier: Framework :: Jupyter :: JupyterLab :: Extensions
Classifier: Framework :: Jupyter :: JupyterLab :: Extensions :: Prebuilt
Classifier: License :: OSI Approved :: BSD License
Classifier: Programming Language :: Python
Classifier: Programming Language :: Python :: 3
Classifier: Programming Language :: Python :: 3.8
Classifier: Programming Language :: Python :: 3.9
Classifier: Programming Language :: Python :: 3.10
Classifier: Programming Language :: Python :: 3.11
Requires-Python: >=3.8
